tcflib/__init__.py
tcflib/service.py
tcflib/tcf.py
tcflib/examples/__init__.py
tcflib/examples/antconc_lemmalist_generator.py
tcflib/examples/csv_exporter.py
tcflib/examples/mallet_exporter.py
tcflib/examples/nltk_tokenizer.py
tcflib/examples/remote_tcf_converter.py
tcflib/examples/testtt.py
tcflib/examples/treetagger.py
tcflib/examples/word_sampler.py
tcflib/tagsets/__init__.py
tcflib/tagsets/base.py
tcflib/tagsets/dc1345.py
tcflib/tagsets/hits.py
tcflib/tagsets/penntb.py
tcflib/tagsets/stein.py
tcflib/tagsets/stts.py
tcflib/tagsets/ud.py
tcflib/tagsets/data/dc-1345.dcif
TCFlib-0.3.1.dist-info/COPYING
TCFlib-0.3.1.dist-info/METADATA
TCFlib-0.3.1.dist-info/WHEEL
TCFlib-0.3.1.dist-info/pbr.json
TCFlib-0.3.1.dist-info/top_level.txt
TCFlib-0.3.1.dist-info/RECORD
