Metadata-Version: 2.1
Name: TCFlib
Version: 0.3.1
Summary: Python TCF library
Home-page: https://github.com/SeNeReKo/TCFlib
Author: Frederik Elwert
Author-email: frederik.elwert@web.de
License-File: COPYING
